urqmd_tools/__init__.py
urqmd_tools/launcher/__init__.py
urqmd_tools/parser/__init__.py
urqmd_tools/parser/f14.py
urqmd_tools/pids/__init__.py
urqmd_tools-0.9.0.dist-info/METADATA
urqmd_tools-0.9.0.dist-info/WHEEL
urqmd_tools-0.9.0.dist-info/entry_points.txt
urqmd_tools-0.9.0.dist-info/top_level.txt
urqmd_tools-0.9.0.dist-info/zip-safe
urqmd_tools-0.9.0.dist-info/RECORD
