Metadata-Version: 2.1
Name: urqmd-tools
Version: 0.9.0
Summary: Python tools that facilitate working with UrQMD
Home-page: https://github.com/pklaus/urqmd-tools
Author: Philipp Klaus
Author-email: klaus@physik.uni-frankfurt.de
License: GPL
Keywords: UrQMD Python Physics Heavy-Ion-Collisions Transport Model
Platform: any
Classifier: Development Status :: 4 - Beta
Classifier: Operating System :: OS Independent
Classifier: License :: OSI Approved :: GNU General Public License v3 or later (GPLv3+)
Classifier: Programming Language :: Python
Classifier: Programming Language :: Python :: 3
Classifier: Topic :: Scientific/Engineering :: Visualization
Requires-Dist: attrs
Requires-Dist: cached-property
